cellopype/__init__.py
cellopype/cell.py
cellopype/helpers.py
cellopype/pype.py
cellopype-0.1.1.dist-info/LICENSE
cellopype-0.1.1.dist-info/METADATA
cellopype-0.1.1.dist-info/WHEEL
cellopype-0.1.1.dist-info/top_level.txt
cellopype-0.1.1.dist-info/RECORD
