Metadata-Version: 2.1
Name: cellopype
Version: 0.1.1
Summary: Build reactive networks using Cells and Pypes.
Author-email: Peter Kleynjan <peter.kleynjan@quantis.nl>
Project-URL: Homepage, https://github.com/kleynjan/cellopype
Project-URL: Bug Tracker, https://github.com/kleynjan/cellopype/issues
Classifier: Programming Language :: Python :: 3
Classifier: License :: OSI Approved :: MIT License
Classifier: Operating System :: OS Independent
Requires-Python: >=3.8
License-File: LICENSE
